transformers_research/__init__.py
transformers_research/version.py
transformers_research/models/__init__.py
transformers_research/models/attention.py
transformers_research/models/norm.py
transformers_research/models/vanilla.py
transformers_research/models/vision.py
transformers_research-0.1.1.dist-info/METADATA
transformers_research-0.1.1.dist-info/WHEEL
transformers_research-0.1.1.dist-info/top_level.txt
transformers_research-0.1.1.dist-info/RECORD
