Metadata-Version: 2.4
Name: transformers-research
Version: 0.1.1
Summary: A package for conducting transformers-related research.
Requires-Python: >=3.11
Requires-Dist: jaxtyping>=0.3.2
Requires-Dist: numpy>=2.3.3
Requires-Dist: torch>=2.8.0
